stdatamodels/__init__.py
stdatamodels/_version.py
stdatamodels/asdf_in_fits.py
stdatamodels/basic_utils.py
stdatamodels/dqflags.py
stdatamodels/dynamicdq.py
stdatamodels/exceptions.py
stdatamodels/filetype.py
stdatamodels/fits_support.py
stdatamodels/history.py
stdatamodels/model_base.py
stdatamodels/properties.py
stdatamodels/schema.py
stdatamodels/util.py
stdatamodels/validate.py
stdatamodels/jwst/__init__.py
stdatamodels/jwst/_kwtool/__init__.py
stdatamodels/jwst/_kwtool/__main__.py
stdatamodels/jwst/_kwtool/cli.py
stdatamodels/jwst/_kwtool/compare.py
stdatamodels/jwst/_kwtool/dmd.py
stdatamodels/jwst/_kwtool/kwd.py
stdatamodels/jwst/_kwtool/_tests/__init__.py
stdatamodels/jwst/_kwtool/_tests/conftest.py
stdatamodels/jwst/_kwtool/_tests/test_against_mast.py
stdatamodels/jwst/_kwtool/_tests/test_cli.py
stdatamodels/jwst/_kwtool/_tests/test_compare.py
stdatamodels/jwst/_kwtool/_tests/test_dmd.py
stdatamodels/jwst/_kwtool/_tests/test_kwd.py
stdatamodels/jwst/_tests/__init__.py
stdatamodels/jwst/_tests/test_schemas.py
stdatamodels/jwst/datamodels/__init__.py
stdatamodels/jwst/datamodels/abvega_offset.py
stdatamodels/jwst/datamodels/amilg.py
stdatamodels/jwst/datamodels/amilgfitmodel.py
stdatamodels/jwst/datamodels/amioi.py
stdatamodels/jwst/datamodels/apcorr.py
stdatamodels/jwst/datamodels/asn.py
stdatamodels/jwst/datamodels/background.py
stdatamodels/jwst/datamodels/barshadow.py
stdatamodels/jwst/datamodels/combinedspec.py
stdatamodels/jwst/datamodels/conftest.py
stdatamodels/jwst/datamodels/contrast.py
stdatamodels/jwst/datamodels/cube.py
stdatamodels/jwst/datamodels/dark.py
stdatamodels/jwst/datamodels/dqflags.py
stdatamodels/jwst/datamodels/emi.py
stdatamodels/jwst/datamodels/extract1d_spec.py
stdatamodels/jwst/datamodels/flat.py
stdatamodels/jwst/datamodels/fringe.py
stdatamodels/jwst/datamodels/fringefreq.py
stdatamodels/jwst/datamodels/gain.py
stdatamodels/jwst/datamodels/guider.py
stdatamodels/jwst/datamodels/ifucube.py
stdatamodels-4.1.0.dist-info/licenses/LICENSE
stdatamodels-4.1.0.dist-info/METADATA
stdatamodels-4.1.0.dist-info/WHEEL
stdatamodels-4.1.0.dist-info/entry_points.txt
stdatamodels-4.1.0.dist-info/top_level.txt
stdatamodels-4.1.0.dist-info/zip-safe
stdatamodels-4.1.0.dist-info/RECORD
